{
  "title": "A comparative analysis of signal processing and classification methods for different applications based on EEG signals",
  "authors": [
    "Ashima Khosla",
    "Padmavati Khandnor",
    "Trilok Chand"
  ],
  "year": 2020,
  "abstract": "",
  "doi": "10.1016/j.bbe.2020.02.002",
  "arxiv_id": null,
  "venue": "Journal of Applied Biomedicine",
  "citation_count": 265,
  "source": "openalex",
  "pdf_url": null,
  "relevance_score": null,
  "extra": {
    "openalex_id": "https://openalex.org/W3007593444"
  },
  "pdf_status": "no_oa",
  "primary_id": "doi:10.1016/j.bbe.2020.02.002",
  "_rejected_reason": "title_block"
}