{
  "title": "Signed Curvature Graph Representation Learning of Brain Networks for Brain Age Estimation.",
  "authors": [
    "Li J",
    "Lyu Z",
    "Yu H",
    "Fu S",
    "Li K",
    "Yao L",
    "Guo X"
  ],
  "year": 2024,
  "abstract": "",
  "doi": "10.1109/JBHI.2024.3434473",
  "arxiv_id": null,
  "venue": "IEEE journal of biomedical and health informatics",
  "citation_count": null,
  "source": "pubmed",
  "pdf_url": null,
  "relevance_score": null,
  "extra": {
    "pmid": "39058614"
  },
  "pdf_status": "no_oa",
  "primary_id": "doi:10.1109/jbhi.2024.3434473"
}